{
    "os": "Linux-5.15.0-83-generic-x86_64-with-glibc2.31",
    "python": "3.9.19",
    "heartbeatAt": "2024-08-31T08:09:38.735610",
    "startedAt": "2024-08-31T08:09:38.024646",
    "docker": null,
    "cuda": null,
    "args": [],
    "state": "running",
    "program": "/home/hlwang/AVDC_change/flowdiffusion/pretrain.py",
    "codePathLocal": "pretrain.py",
    "codePath": "pretrain.py",
    "git": {
        "remote": "https://github.com/whl23333/AVDC_change.git",
        "commit": "5e85a5a1347215f8607203a1e58ad15459a620f4"
    },
    "email": "whl@nc1663.onexmail.com",
    "root": "/home/hlwang/AVDC_change/flowdiffusion",
    "host": "user-SYS-420GP-TNR",
    "username": "hlwang",
    "executable": "/home/hlwang/miniconda3/envs/env/bin/python",
    "cpu_count": 32,
    "cpu_count_logical": 64,
    "cpu_freq": {
        "current": 2899.0788593750003,
        "min": 800.0,
        "max": 3400.0
    },
    "cpu_freq_per_core": [
        {
            "current": 2600.0,
            "min": 800.0,
            "max": 3400.0
        },
        {
            "current": 3079.978,
            "min": 800.0,
            "max": 3400.0
        },
        {
            "current": 3080.274,
            "min": 800.0,
            "max": 3400.0
        },
        {
            "current": 3400.0,
            "min": 800.0,
            "max": 3400.0
        },
        {
            "current": 3065.852,
            "min": 800.0,
            "max": 3400.0
        },
        {
            "current": 3400.0,
            "min": 800.0,
            "max": 3400.0
        },
        {
            "current": 3400.0,
            "min": 800.0,
            "max": 3400.0
        },
        {
            "current": 3083.247,
            "min": 800.0,
            "max": 3400.0
        },
        {
            "current": 3400.0,
            "min": 800.0,
            "max": 3400.0
        },
        {
            "current": 3084.27,
            "min": 800.0,
            "max": 3400.0
        },
        {
            "current": 3400.0,
            "min": 800.0,
            "max": 3400.0
        },
        {
            "current": 2400.0,
            "min": 800.0,
            "max": 3400.0
        },
        {
            "current": 3400.0,
            "min": 800.0,
            "max": 3400.0
        },
        {
            "current": 3400.0,
            "min": 800.0,
            "max": 3400.0
        },
        {
            "current": 3028.081,
            "min": 800.0,
            "max": 3400.0
        },
        {
            "current": 2828.183,
            "min": 800.0,
            "max": 3400.0
        },
        {
            "current": 2900.002,
            "min": 800.0,
            "max": 3400.0
        },
        {
            "current": 2899.997,
            "min": 800.0,
            "max": 3400.0
        },
        {
            "current": 2900.0,
            "min": 800.0,
            "max": 3400.0
        },
        {
            "current": 2900.0,
            "min": 800.0,
            "max": 3400.0
        },
        {
            "current": 2900.0,
            "min": 800.0,
            "max": 3400.0
        },
        {
            "current": 2900.0,
            "min": 800.0,
            "max": 3400.0
        },
        {
            "current": 2899.997,
            "min": 800.0,
            "max": 3400.0
        },
        {
            "current": 2899.995,
            "min": 800.0,
            "max": 3400.0
        },
        {
            "current": 2900.0,
            "min": 800.0,
            "max": 3400.0
        },
        {
            "current": 2900.0,
            "min": 800.0,
            "max": 3400.0
        },
        {
            "current": 2900.0,
            "min": 800.0,
            "max": 3400.0
        },
        {
            "current": 2900.0,
            "min": 800.0,
            "max": 3400.0
        },
        {
            "current": 2900.0,
            "min": 800.0,
            "max": 3400.0
        },
        {
            "current": 2900.0,
            "min": 800.0,
            "max": 3400.0
        },
        {
            "current": 2900.0,
            "min": 800.0,
            "max": 3400.0
        },
        {
            "current": 2900.0,
            "min": 800.0,
            "max": 3400.0
        },
        {
            "current": 3400.0,
            "min": 800.0,
            "max": 3400.0
        },
        {
            "current": 3097.534,
            "min": 800.0,
            "max": 3400.0
        },
        {
            "current": 3400.0,
            "min": 800.0,
            "max": 3400.0
        },
        {
            "current": 3098.642,
            "min": 800.0,
            "max": 3400.0
        },
        {
            "current": 1600.0,
            "min": 800.0,
            "max": 3400.0
        },
        {
            "current": 3400.0,
            "min": 800.0,
            "max": 3400.0
        },
        {
            "current": 3400.0,
            "min": 800.0,
            "max": 3400.0
        },
        {
            "current": 3101.0,
            "min": 800.0,
            "max": 3400.0
        },
        {
            "current": 3101.333,
            "min": 800.0,
            "max": 3400.0
        },
        {
            "current": 3102.203,
            "min": 800.0,
            "max": 3400.0
        },
        {
            "current": 3400.0,
            "min": 800.0,
            "max": 3400.0
        },
        {
            "current": 1600.0,
            "min": 800.0,
            "max": 3400.0
        },
        {
            "current": 2500.0,
            "min": 800.0,
            "max": 3400.0
        },
        {
            "current": 3200.0,
            "min": 800.0,
            "max": 3400.0
        },
        {
            "current": 3400.0,
            "min": 800.0,
            "max": 3400.0
        },
        {
            "current": 3400.0,
            "min": 800.0,
            "max": 3400.0
        },
        {
            "current": 2900.0,
            "min": 800.0,
            "max": 3400.0
        },
        {
            "current": 2899.997,
            "min": 800.0,
            "max": 3400.0
        },
        {
            "current": 2900.0,
            "min": 800.0,
            "max": 3400.0
        },
        {
            "current": 2900.0,
            "min": 800.0,
            "max": 3400.0
        },
        {
            "current": 2900.0,
            "min": 800.0,
            "max": 3400.0
        },
        {
            "current": 2900.0,
            "min": 800.0,
            "max": 3400.0
        },
        {
            "current": 2899.997,
            "min": 800.0,
            "max": 3400.0
        },
        {
            "current": 2900.0,
            "min": 800.0,
            "max": 3400.0
        },
        {
            "current": 2900.0,
            "min": 800.0,
            "max": 3400.0
        },
        {
            "current": 2900.0,
            "min": 800.0,
            "max": 3400.0
        },
        {
            "current": 2900.0,
            "min": 800.0,
            "max": 3400.0
        },
        {
            "current": 2900.0,
            "min": 800.0,
            "max": 3400.0
        },
        {
            "current": 2900.0,
            "min": 800.0,
            "max": 3400.0
        },
        {
            "current": 2900.0,
            "min": 800.0,
            "max": 3400.0
        },
        {
            "current": 2899.997,
            "min": 800.0,
            "max": 3400.0
        },
        {
            "current": 2900.0,
            "min": 800.0,
            "max": 3400.0
        }
    ],
    "disk": {
        "/": {
            "total": 3519.256721496582,
            "used": 3061.526153564453
        }
    },
    "gpu": "NVIDIA GeForce RTX 3090",
    "gpu_count": 8,
    "gpu_devices": [
        {
            "name": "NVIDIA GeForce RTX 3090",
            "memory_total": 25769803776
        },
        {
            "name": "NVIDIA GeForce RTX 3090",
            "memory_total": 25769803776
        },
        {
            "name": "NVIDIA GeForce RTX 3090",
            "memory_total": 25769803776
        },
        {
            "name": "NVIDIA GeForce RTX 3090",
            "memory_total": 25769803776
        },
        {
            "name": "NVIDIA GeForce RTX 3090",
            "memory_total": 25769803776
        },
        {
            "name": "NVIDIA GeForce RTX 3090",
            "memory_total": 25769803776
        },
        {
            "name": "NVIDIA GeForce RTX 3090",
            "memory_total": 25769803776
        },
        {
            "name": "NVIDIA GeForce RTX 3090",
            "memory_total": 25769803776
        }
    ],
    "memory": {
        "total": 503.53164291381836
    }
}
